cleverminer/__init__.py
cleverminer/actplusminer.py
cleverminer/cleverminer.py
cleverminer/clmec.py
cleverminer-1.2.5.dist-info/licenses/LICENSE
cleverminer-1.2.5.dist-info/METADATA
cleverminer-1.2.5.dist-info/WHEEL
cleverminer-1.2.5.dist-info/top_level.txt
cleverminer-1.2.5.dist-info/RECORD
