Metadata-Version: 2.4
Name: cleverminer
Version: 1.2.5
Summary: Beyond apriori. CleverMiner is the package for enhanced association rule mining (eARM). Comparing to standard association rules, it is very enhanced, because the package implements the GUHA procedures that generalizes apriori and association rules in many ways. Rules are based on categorical data that can be easily visualized and interpreted. Their if-then with probability allows easy deployment by human realized processes. Interpretable & explainable knowledge mining.
Home-page: https://cleverminer.org
Author: (C) Copyright 2020 - 2025 Petr Masa
Author-email: code@cleverminer.org
Classifier: Programming Language :: Python :: 3
Classifier: Programming Language :: Python :: 3.10
Classifier: Programming Language :: Python :: 3.11
Classifier: Programming Language :: Python :: 3.12
Classifier: Programming Language :: Python :: 3.13
Classifier: Development Status :: 5 - Production/Stable
Classifier: License :: OSI Approved :: GNU General Public License v3 (GPLv3)
Classifier: Operating System :: OS Independent
Requires-Python: >=3.8
License-File: LICENSE
Requires-Dist: progressbar2
Requires-Dist: pandas
Requires-Dist: numpy
Requires-Dist: matplotlib
Requires-Dist: seaborn
Dynamic: author
Dynamic: author-email
Dynamic: classifier
Dynamic: description
Dynamic: description-content-type
Dynamic: home-page
Dynamic: license-file
Dynamic: requires-dist
Dynamic: requires-python
Dynamic: summary
